src/__init__.py
src/apyrat.py
src/cli.py
src/utils.py
apyrat-0.2.2.dist-info/METADATA
apyrat-0.2.2.dist-info/WHEEL
apyrat-0.2.2.dist-info/entry_points.txt
apyrat-0.2.2.dist-info/licenses/LICENSE
apyrat-0.2.2.dist-info/RECORD
