Metadata-Version: 2.4
Name: apyrat
Version: 0.2.2
Summary: An Aparat video downloader. simple, but elegant.
Project-URL: Homepage, https://github.com/codewithemad/apyrat
Project-URL: Issues, https://github.com/codewithemad/apyrat/issues
Author: Emad Rad
Author-email: codewithemad@gmail.com
License: MIT License
License-File: LICENSE
Classifier: Development Status :: 5 - Production/Stable
Classifier: License :: OSI Approved :: MIT License
Classifier: Operating System :: OS Independent
Classifier: Programming Language :: Python
Classifier: Programming Language :: Python :: 3.8
Classifier: Programming Language :: Python :: 3.9
Classifier: Programming Language :: Python :: 3.10
Classifier: Programming Language :: Python :: 3.11
Classifier: Programming Language :: Python :: 3.12
Classifier: Programming Language :: Python :: 3.13
Requires-Python: >=3.8
Requires-Dist: click>=8.0.4
Requires-Dist: requests>=2.31.0
Requires-Dist: wget>=3.2
Provides-Extra: dev
Requires-Dist: coverage>=7.2.7; extra == 'dev'
Requires-Dist: pytest-sugar>=1.0.0; extra == 'dev'
Requires-Dist: pytest>=7.4.4; extra == 'dev'
Requires-Dist: ruff>=0.9.7; extra == 'dev'
